{
	"debug": true,
	"baseUrl": "http://localhost:8000",
	"port": 8000,
	"couchdb": {
		"host": "localhost",
		"port": 5984,
		"bucket": "monitool",
		"sessionBucket": "monitool-sessions",
		"username": "",
		"password": ""
	},
	"auth": {
		"administrator": "romain.gilliotte",
		"azureAD": {
			"label": "Use MDM account",
			"domain": "medecinsdumonde.net",
			"clientId": "[enter client id]",
			"clientSecret": "[enter client secret]"
		},
		"training": {
			"label": "Use training account (admin)",
			"account": "romain.gilliotte"
		}
	}
}
